setup.cfg
setup.py
packagesubnet/__init__.py
packagesubnet/my_subnet_librairy.py
packagesubnet.egg-info/PKG-INFO
packagesubnet.egg-info/SOURCES.txt
packagesubnet.egg-info/dependency_links.txt
packagesubnet.egg-info/top_level.txt