Metadata-Version: 1.1
Name: packagesubnet
Version: 0.7
Summary: A random test lib
Home-page: https://github.com/mlapeyre73/packagesubnet
Author: marian laeyre
Author-email: peterldowns@gmail.com
License: MIT
Download-URL: https://github.com/mlapeyre73/packagesubnetarchive/0.1.tar.gz
Keywords: testing,logging,example
Platform: UNKNOWN
Classifier: Development Status :: 3 - Alpha
Classifier: Intended Audience :: Developers
Classifier: Topic :: Software Development :: Build Tools
Classifier: License :: OSI Approved :: MIT License
Classifier: Programming Language :: Python :: 2
Classifier: Programming Language :: Python :: 2.7
Classifier: Programming Language :: Python :: 3
Classifier: Programming Language :: Python :: 3.3
Classifier: Programming Language :: Python :: 3.4
Classifier: Programming Language :: Python :: 3.5
